yt_audio_cli/__init__.py
yt_audio_cli/__main__.py
yt_audio_cli/cli.py
yt_audio_cli/batch/__init__.py
yt_audio_cli/batch/executor.py
yt_audio_cli/batch/job.py
yt_audio_cli/batch/request.py
yt_audio_cli/batch/retry.py
yt_audio_cli/convert/__init__.py
yt_audio_cli/convert/transcoder.py
yt_audio_cli/core/__init__.py
yt_audio_cli/core/errors.py
yt_audio_cli/core/filename.py
yt_audio_cli/download/__init__.py
yt_audio_cli/download/batch.py
yt_audio_cli/download/downloader.py
yt_audio_cli/ui/__init__.py
yt_audio_cli/ui/progress.py
yt_audio_cli-0.2.0.dist-info/METADATA
yt_audio_cli-0.2.0.dist-info/WHEEL
yt_audio_cli-0.2.0.dist-info/entry_points.txt
yt_audio_cli-0.2.0.dist-info/licenses/LICENSE
yt_audio_cli-0.2.0.dist-info/RECORD
