Metadata-Version: 2.4
Name: yt-audio-cli
Version: 0.2.0
Summary: A simple command-line tool for downloading audio from YouTube and other sites
License-Expression: MIT
License-File: LICENSE
Classifier: Development Status :: 4 - Beta
Classifier: Environment :: Console
Classifier: Intended Audience :: End Users/Desktop
Classifier: License :: OSI Approved :: MIT License
Classifier: Operating System :: OS Independent
Classifier: Programming Language :: Python :: 3
Classifier: Programming Language :: Python :: 3.12
Classifier: Programming Language :: Python :: 3.13
Classifier: Topic :: Multimedia :: Sound/Audio
Requires-Python: >=3.12
Requires-Dist: rich>=14.2.0
Requires-Dist: typer>=0.21.0
Requires-Dist: yt-dlp>=2025.12.8
